{
  "company": "reddit",
  "common_questions": [
    "Do you Have any other questions for us?",
    "How much of your code is written by contractors?",
    "what percentage of your code is written in house?",
    "me if I had anymore questions and I straight out said, “when do I start?",
    "explain so you can decide which",
    "explain in future interviews if I don’t have enough details to explain (don’t want to l",
    "explains the solutions to problems so that I could pull off something similar when expl",
    "explain every detail of my thought process",
    "explained to them that they were being scammed and went back to my tennis session",
    "explain your approach to building things",
    "tell me about yourself“ answer and recite it",
    "why do you want a dev job?",
    "explained that I felt that I was confident in my skills and really felt that i got the",
    "explained that the assessments were made to provide an equal assessment of candidate's",
    "explains coding and algorithms, which you can anyway buy separately for $67 if really i"
  ],
  "themes": [
    "System design emphasis",
    "Heavy focus on coding",
    "Behavioral interviews important",
    "Culture fit matters",
    "Technical deep dive",
    "Case study format",
    "Multiple interview rounds",
    "Take-home assignment"
  ],
  "interview_tips": [
    "picking a few blocks of time even if you don’t really need to be that restrictive",
    "from a career blog a few years ago, and ever since, this question has been with me in every interview I do",
    "speak with your manager BEFORE your first day of work",
    "to spread the word everywhere you can that this job will fire you on the spot if you seek other employment",
    "you show them you have all it takes",
    "here to build confidence and focus on what you can control yourself",
    "doing is cutting off the interviewer and pressing them for time though",
    "and do better next time",
    "on how to do well in interviews and CVs",
    "for those still struggling to get where OP is right now would be to use tour resources and utilize people for knowledge transfer"
  ],
  "red_flags": [
    "wear my clothes more than once between washings",
    "really care if they are late, all good",
    "know the deadline for the applications or how long it's going to take to choose the next stage candidates, and any answer other than \"anytime\" or \"I'm",
    "use reddit on web and transferring a screenshot to my phone is long asf",
    "give them all these options",
    "think anyone in my building even knows what I do anymore,\" or \"The hierarchy of managers to whom I report has become increasingly unclear",
    "unless they want you to leave and keep your severance",
    "team structure, company culture questions because they’re tired of answering it"
  ],
  "process_insights": {
    "typical_rounds": "4 rounds typical",
    "timeline": "2-4 weeks",
    "format": "Mix of phone screen, technical, behavioral, on-site, virtual"
  },
  "source_count": 57
}